jhfunnycode/__init__.py
jhfunnycode/fun.py
jhfunnycode-1.4.1.dist-info/METADATA
jhfunnycode-1.4.1.dist-info/WHEEL
jhfunnycode-1.4.1.dist-info/top_level.txt
jhfunnycode-1.4.1.dist-info/RECORD
