Metadata-Version: 2.1
Name: jhfunnycode
Version: 1.4.1
Summary: life is fun
Home-page: UNKNOWN
Author: i_enable
License: UNKNOWN
Platform: UNKNOWN
